cipherdeck/__init__.py
cipherdeck/alphabet.py
cipherdeck/viginere.py
cipherdeck-0.1.0.dist-info/LICENSE
cipherdeck-0.1.0.dist-info/METADATA
cipherdeck-0.1.0.dist-info/WHEEL
cipherdeck-0.1.0.dist-info/entry_points.txt
cipherdeck-0.1.0.dist-info/top_level.txt
cipherdeck-0.1.0.dist-info/RECORD
